htest_tools/__init__.py
htest_tools/estimator_properties.py
htest_tools/htests.py
htest_tools/mle_est.py
htest_tools/np_lemma_tests.py
htest_tools-0.2.8.dist-info/METADATA
htest_tools-0.2.8.dist-info/WHEEL
htest_tools-0.2.8.dist-info/top_level.txt
htest_tools-0.2.8.dist-info/RECORD
