Metadata-Version: 2.4
Name: htest-tools
Version: 0.2.8
Summary: Simple Z-test helper functions (one mean and two proportions)
Author: Rajesh kane
Requires-Python: >=3.8
Requires-Dist: scipy
